ScheduleGenius/ScheduleGenius.py
ScheduleGenius-0.0.1.dist-info/LICENSE
ScheduleGenius-0.0.1.dist-info/METADATA
ScheduleGenius-0.0.1.dist-info/WHEEL
ScheduleGenius-0.0.1.dist-info/top_level.txt
ScheduleGenius-0.0.1.dist-info/RECORD
