Metadata-Version: 2.1
Name: ScheduleGenius
Version: 0.0.1
Summary: nice calculator
Home-page: https://github.com/duqordl/my-oss
Download-URL: https://github.com/duqordl/my-oss
Author: jihyeon
Classifier: Programming Language :: Python :: 3
License-File: LICENSE
